enterprython/__init__.py
enterprython/_inject.py
enterprython/py.typed
enterprython/tests.py
enterprython-0.7.0.dist-info/LICENSE
enterprython-0.7.0.dist-info/METADATA
enterprython-0.7.0.dist-info/WHEEL
enterprython-0.7.0.dist-info/top_level.txt
enterprython-0.7.0.dist-info/RECORD
