Metadata-Version: 2.1
Name: enterprython
Version: 0.7.0
Summary: Type-based dependency injection
Home-page: http://github.com/Dobiasd/enterprython
Author: Tobias Hermann
Author-email: editgym@gmail.com
License: UNKNOWN
Platform: UNKNOWN
Classifier: Programming Language :: Python :: 3.7
Classifier: License :: OSI Approved :: MIT License
Classifier: Operating System :: OS Independent
